pylspci/__init__.py
pylspci/__main__.py
pylspci/command.py
pylspci/device.py
pylspci/fields.py
pylspci/filters.py
pylspci/py.typed
pylspci/parsers/__init__.py
pylspci/parsers/base.py
pylspci/parsers/simple.py
pylspci/parsers/verbose.py
pylspci-0.4.3.dist-info/LICENSE
pylspci-0.4.3.dist-info/METADATA
pylspci-0.4.3.dist-info/WHEEL
pylspci-0.4.3.dist-info/entry_points.txt
pylspci-0.4.3.dist-info/top_level.txt
pylspci-0.4.3.dist-info/RECORD
